{"version":"https://jsonfeed.org/version/1.1","title":"hugo-blog - 标签 | 菠菜眾長","description":"Hugo FixIt 作者，喜欢瞎折腾、造轮子、写东西，分享一些前端开发中的所见、所闻、所思。","home_page_url":"https://lruihao.cn/","language":"zh-CN","icon":"https://lruihao.cn/apple-touch-icon.png","favicon":"https://lruihao.cn/favicon.ico","authors":[{"name":"Lruihao","url":"https://github.com/Lruihao","avatar":"https://lruihao.cn/images/avatar.jpg"}],"items":[{"title":"🆕 A quick-start template base on Hugo Modules to create a Hugo FixIt site.","date_published":"2022-09-30T09:28:41Z","date_modified":"2026-03-20T01:00:02Z","id":"https://lruihao.cn/projects/hugo-fixit/hugo-fixit-starter/","url":"https://lruihao.cn/projects/hugo-fixit/hugo-fixit-starter/","authors":[{"name":"hugo-fixit","url":"https://github.com/hugo-fixit","avatar":"https://avatars.githubusercontent.com/u/110414864?v=4"}],"tags":["blog","hugo-blog","hugo-blog-template","hugo-fixit","hugo-fixit-starter"],"summary":"Hugo FixIt 博客模板（Go） 👉 中文 | English\n这是 Hugo 主题 FixIt 的快速启动模板。它使用 Hugo 模块 功能加载主题。如果你更熟悉 Git，可以 查看这个模板。\n它提供了基本的主题结构和 配置目录1。已经设置了 GitHub Actions，可以自动部署博客到 GitHub Pages。此外，还有一个定时任务，每天自动更新主题。\n目录结构 ▸ .github/ # GitHub configuration ▸ archetypes/ # page archetypes (like scaffolds of archetypes) ▸ assets/ # css, js, third-party libraries etc. ▸ config/ # configuration files ▸ content/ # markdown files for hugo project ▸ data/ # blog data (allow: yaml, json, toml), e.g. friends.yml ▸ public/ # build directory ▸ static/ # static files, e.g. favicon.ico ▸ themes/ # theme submodules ▸ go.mod ▸ go.sum快速入门 完整的快速入门，请参阅此 页面。\n","content_html":"\u003ch2 class=\"heading-element\" id=\"hugo-fixit-博客模板go\" data-decreased\u003e\u003cspan\u003eHugo FixIt 博客模板（Go）\u003c/span\u003e\n  \u003ca href=\"#hugo-fixit-%e5%8d%9a%e5%ae%a2%e6%a8%a1%e6%9d%bfgo\" class=\"heading-mark\"\u003e\n    \u003csvg class=\"octicon octicon-link\" viewBox=\"0 0 16 16\" version=\"1.1\" width=\"16\" height=\"16\" aria-hidden=\"true\"\u003e\u003cpath d=\"m7.775 3.275 1.25-1.25a3.5 3.5 0 1 1 4.95 4.95l-2.5 2.5a3.5 3.5 0 0 1-4.95 0 .751.751 0 0 1 .018-1.042.751.751 0 0 1 1.042-.018 1.998 1.998 0 0 0 2.83 0l2.5-2.5a2.002 2.002 0 0 0-2.83-2.83l-1.25 1.25a.751.751 0 0 1-1.042-.018.751.751 0 0 1-.018-1.042Zm-4.69 9.64a1.998 1.998 0 0 0 2.83 0l1.25-1.25a.751.751 0 0 1 1.042.018.751.751 0 0 1 .018 1.042l-1.25 1.25a3.5 3.5 0 1 1-4.95-4.95l2.5-2.5a3.5 3.5 0 0 1 4.95 0 .751.751 0 0 1-.018 1.042.751.751 0 0 1-1.042.018 1.998 1.998 0 0 0-2.83 0l-2.5 2.5a1.998 1.998 0 0 0 0 2.83Z\"\u003e\u003c/path\u003e\u003c/svg\u003e\n  \u003c/a\u003e\n\u003c/h2\u003e\u003cp\u003e👉 中文 | \u003ca href=\"README.en.md\"\u003eEnglish\u003c/a\u003e\u003c/p\u003e\n\u003cp\u003e这是 Hugo 主题 \u003ca href=\"https://github.com/hugo-fixit/FixIt\" target=\"_blank\" rel=\"external nofollow noopener noreferrer\"\u003eFixIt\u003ci class=\"fa-solid fa-external-link-alt fa-xs ms-1 text-secondary\" aria-hidden=\"true\"\u003e\u003c/i\u003e\u003c/a\u003e 的快速启动模板。它使用 \u003ca href=\"https://gohugo.io/hugo-modules/\" target=\"_blank\" rel=\"external nofollow noopener noreferrer\"\u003eHugo 模块\u003ci class=\"fa-solid fa-external-link-alt fa-xs ms-1 text-secondary\" aria-hidden=\"true\"\u003e\u003c/i\u003e\u003c/a\u003e 功能加载主题。如果你更熟悉 Git，可以 \u003ca href=\"https://github.com/hugo-fixit/hugo-fixit-starter1\" target=\"_blank\" rel=\"external nofollow noopener noreferrer\"\u003e查看这个模板\u003ci class=\"fa-solid fa-external-link-alt fa-xs ms-1 text-secondary\" aria-hidden=\"true\"\u003e\u003c/i\u003e\u003c/a\u003e。\u003c/p\u003e\n\u003cp\u003e它提供了基本的主题结构和 \u003ca href=\"https://gohugo.io/configuration/introduction/#configuration-directory\" target=\"_blank\" rel=\"external nofollow noopener noreferrer\"\u003e配置目录\u003ci class=\"fa-solid fa-external-link-alt fa-xs ms-1 text-secondary\" aria-hidden=\"true\"\u003e\u003c/i\u003e\u003c/a\u003e\u003csup id=\"fnref:1\"\u003e\u003ca href=\"#fn:1\" class=\"footnote-ref\" role=\"doc-noteref\"\u003e1\u003c/a\u003e\u003c/sup\u003e。已经设置了 GitHub Actions，可以自动部署博客到 GitHub Pages。此外，还有一个定时任务，每天自动更新主题。\u003c/p\u003e\n\u003ch2 class=\"heading-element\" id=\"目录结构\"\u003e\u003cspan\u003e目录结构\u003c/span\u003e\n  \u003ca href=\"#%e7%9b%ae%e5%bd%95%e7%bb%93%e6%9e%84\" class=\"heading-mark\"\u003e\n    \u003csvg class=\"octicon octicon-link\" viewBox=\"0 0 16 16\" version=\"1.1\" width=\"16\" height=\"16\" aria-hidden=\"true\"\u003e\u003cpath d=\"m7.775 3.275 1.25-1.25a3.5 3.5 0 1 1 4.95 4.95l-2.5 2.5a3.5 3.5 0 0 1-4.95 0 .751.751 0 0 1 .018-1.042.751.751 0 0 1 1.042-.018 1.998 1.998 0 0 0 2.83 0l2.5-2.5a2.002 2.002 0 0 0-2.83-2.83l-1.25 1.25a.751.751 0 0 1-1.042-.018.751.751 0 0 1-.018-1.042Zm-4.69 9.64a1.998 1.998 0 0 0 2.83 0l1.25-1.25a.751.751 0 0 1 1.042.018.751.751 0 0 1 .018 1.042l-1.25 1.25a3.5 3.5 0 1 1-4.95-4.95l2.5-2.5a3.5 3.5 0 0 1 4.95 0 .751.751 0 0 1-.018 1.042.751.751 0 0 1-1.042.018 1.998 1.998 0 0 0-2.83 0l-2.5 2.5a1.998 1.998 0 0 0 0 2.83Z\"\u003e\u003c/path\u003e\u003c/svg\u003e\n  \u003c/a\u003e\n\u003c/h2\u003e\u003cpre\u003e\u003ccode\u003e▸ .github/       # GitHub configuration\n▸ archetypes/    # page archetypes (like scaffolds of archetypes)\n▸ assets/        # css, js, third-party libraries etc.\n▸ config/        # configuration files\n▸ content/       # markdown files for hugo project\n▸ data/          # blog data (allow: yaml, json, toml), e.g. friends.yml\n▸ public/        # build directory\n▸ static/        # static files, e.g. favicon.ico\n▸ themes/        # theme submodules\n▸ go.mod\n▸ go.sum\u003c/code\u003e\u003c/pre\u003e\u003ch2 class=\"heading-element\" id=\"快速入门\"\u003e\u003cspan\u003e快速入门\u003c/span\u003e\n  \u003ca href=\"#%e5%bf%ab%e9%80%9f%e5%85%a5%e9%97%a8\" class=\"heading-mark\"\u003e\n    \u003csvg class=\"octicon octicon-link\" viewBox=\"0 0 16 16\" version=\"1.1\" width=\"16\" height=\"16\" aria-hidden=\"true\"\u003e\u003cpath d=\"m7.775 3.275 1.25-1.25a3.5 3.5 0 1 1 4.95 4.95l-2.5 2.5a3.5 3.5 0 0 1-4.95 0 .751.751 0 0 1 .018-1.042.751.751 0 0 1 1.042-.018 1.998 1.998 0 0 0 2.83 0l2.5-2.5a2.002 2.002 0 0 0-2.83-2.83l-1.25 1.25a.751.751 0 0 1-1.042-.018.751.751 0 0 1-.018-1.042Zm-4.69 9.64a1.998 1.998 0 0 0 2.83 0l1.25-1.25a.751.751 0 0 1 1.042.018.751.751 0 0 1 .018 1.042l-1.25 1.25a3.5 3.5 0 1 1-4.95-4.95l2.5-2.5a3.5 3.5 0 0 1 4.95 0 .751.751 0 0 1-.018 1.042.751.751 0 0 1-1.042.018 1.998 1.998 0 0 0-2.83 0l-2.5 2.5a1.998 1.998 0 0 0 0 2.83Z\"\u003e\u003c/path\u003e\u003c/svg\u003e\n  \u003c/a\u003e\n\u003c/h2\u003e\u003cp\u003e完整的快速入门，请参阅此 \u003ca href=\"https://fixit.lruihao.cn/documentation/getting-started/\" target=\"_blank\" rel=\"external nofollow noopener noreferrer\"\u003e页面\u003ci class=\"fa-solid fa-external-link-alt fa-xs ms-1 text-secondary\" aria-hidden=\"true\"\u003e\u003c/i\u003e\u003c/a\u003e。\u003c/p\u003e"},{"title":"🆕 A quick-start template base on Git submodule to create a Hugo FixIt site.","date_published":"2022-09-27T15:23:38Z","date_modified":"2026-03-20T01:03:51Z","id":"https://lruihao.cn/projects/hugo-fixit/hugo-fixit-starter1/","url":"https://lruihao.cn/projects/hugo-fixit/hugo-fixit-starter1/","authors":[{"name":"hugo-fixit","url":"https://github.com/hugo-fixit","avatar":"https://avatars.githubusercontent.com/u/110414864?v=4"}],"tags":["blog","hugo-blog","hugo-blog-template","hugo-fixit","hugo-fixit-starter"],"summary":"Hugo FixIt 博客模板（Git） 👉 中文 | English\n这是 Hugo 主题 FixIt 的快速启动模板。它使用 Git 子模块 功能来加载主题。如果你更熟悉 Go，可以 查看这个模板。\n它提供了基本的主题结构和 配置目录1。已经设置了 GitHub Actions，可以自动部署博客到 GitHub Pages。此外，还有一个定时任务，每天自动更新主题。\n目录结构 ▸ .github/ # GitHub configuration ▸ archetypes/ # page archetypes (like scaffolds of archetypes) ▸ assets/ # css, js, third-party libraries etc. ▸ config/ # configuration files ▸ content/ # markdown files for hugo project ▸ data/ # blog data (allow: yaml, json, toml), e.g. friends.yml ▸ public/ # build directory ▸ static/ # static files, e.g. favicon.ico ▸ themes/ # theme submodules快速入门 完整的快速入门请参阅此 页面。\n","content_html":"\u003ch2 class=\"heading-element\" id=\"hugo-fixit-博客模板git\" data-decreased\u003e\u003cspan\u003eHugo FixIt 博客模板（Git）\u003c/span\u003e\n  \u003ca href=\"#hugo-fixit-%e5%8d%9a%e5%ae%a2%e6%a8%a1%e6%9d%bfgit\" class=\"heading-mark\"\u003e\n    \u003csvg class=\"octicon octicon-link\" viewBox=\"0 0 16 16\" version=\"1.1\" width=\"16\" height=\"16\" aria-hidden=\"true\"\u003e\u003cpath d=\"m7.775 3.275 1.25-1.25a3.5 3.5 0 1 1 4.95 4.95l-2.5 2.5a3.5 3.5 0 0 1-4.95 0 .751.751 0 0 1 .018-1.042.751.751 0 0 1 1.042-.018 1.998 1.998 0 0 0 2.83 0l2.5-2.5a2.002 2.002 0 0 0-2.83-2.83l-1.25 1.25a.751.751 0 0 1-1.042-.018.751.751 0 0 1-.018-1.042Zm-4.69 9.64a1.998 1.998 0 0 0 2.83 0l1.25-1.25a.751.751 0 0 1 1.042.018.751.751 0 0 1 .018 1.042l-1.25 1.25a3.5 3.5 0 1 1-4.95-4.95l2.5-2.5a3.5 3.5 0 0 1 4.95 0 .751.751 0 0 1-.018 1.042.751.751 0 0 1-1.042.018 1.998 1.998 0 0 0-2.83 0l-2.5 2.5a1.998 1.998 0 0 0 0 2.83Z\"\u003e\u003c/path\u003e\u003c/svg\u003e\n  \u003c/a\u003e\n\u003c/h2\u003e\u003cp\u003e👉 中文 | \u003ca href=\"README.en.md\"\u003eEnglish\u003c/a\u003e\u003c/p\u003e\n\u003cp\u003e这是 Hugo 主题 \u003ca href=\"https://github.com/hugo-fixit/FixIt\" target=\"_blank\" rel=\"external nofollow noopener noreferrer\"\u003eFixIt\u003ci class=\"fa-solid fa-external-link-alt fa-xs ms-1 text-secondary\" aria-hidden=\"true\"\u003e\u003c/i\u003e\u003c/a\u003e 的快速启动模板。它使用 \u003ca href=\"https://git-scm.com/book/en/v2/Git-Tools-Submodules\" target=\"_blank\" rel=\"external nofollow noopener noreferrer\"\u003eGit 子模块\u003ci class=\"fa-solid fa-external-link-alt fa-xs ms-1 text-secondary\" aria-hidden=\"true\"\u003e\u003c/i\u003e\u003c/a\u003e 功能来加载主题。如果你更熟悉 Go，可以 \u003ca href=\"https://github.com/hugo-fixit/hugo-fixit-starter\" target=\"_blank\" rel=\"external nofollow noopener noreferrer\"\u003e查看这个模板\u003ci class=\"fa-solid fa-external-link-alt fa-xs ms-1 text-secondary\" aria-hidden=\"true\"\u003e\u003c/i\u003e\u003c/a\u003e。\u003c/p\u003e\n\u003cp\u003e它提供了基本的主题结构和 \u003ca href=\"https://gohugo.io/configuration/introduction/#configuration-directory\" target=\"_blank\" rel=\"external nofollow noopener noreferrer\"\u003e配置目录\u003ci class=\"fa-solid fa-external-link-alt fa-xs ms-1 text-secondary\" aria-hidden=\"true\"\u003e\u003c/i\u003e\u003c/a\u003e\u003csup id=\"fnref:1\"\u003e\u003ca href=\"#fn:1\" class=\"footnote-ref\" role=\"doc-noteref\"\u003e1\u003c/a\u003e\u003c/sup\u003e。已经设置了 GitHub Actions，可以自动部署博客到 GitHub Pages。此外，还有一个定时任务，每天自动更新主题。\u003c/p\u003e\n\u003ch2 class=\"heading-element\" id=\"目录结构\"\u003e\u003cspan\u003e目录结构\u003c/span\u003e\n  \u003ca href=\"#%e7%9b%ae%e5%bd%95%e7%bb%93%e6%9e%84\" class=\"heading-mark\"\u003e\n    \u003csvg class=\"octicon octicon-link\" viewBox=\"0 0 16 16\" version=\"1.1\" width=\"16\" height=\"16\" aria-hidden=\"true\"\u003e\u003cpath d=\"m7.775 3.275 1.25-1.25a3.5 3.5 0 1 1 4.95 4.95l-2.5 2.5a3.5 3.5 0 0 1-4.95 0 .751.751 0 0 1 .018-1.042.751.751 0 0 1 1.042-.018 1.998 1.998 0 0 0 2.83 0l2.5-2.5a2.002 2.002 0 0 0-2.83-2.83l-1.25 1.25a.751.751 0 0 1-1.042-.018.751.751 0 0 1-.018-1.042Zm-4.69 9.64a1.998 1.998 0 0 0 2.83 0l1.25-1.25a.751.751 0 0 1 1.042.018.751.751 0 0 1 .018 1.042l-1.25 1.25a3.5 3.5 0 1 1-4.95-4.95l2.5-2.5a3.5 3.5 0 0 1 4.95 0 .751.751 0 0 1-.018 1.042.751.751 0 0 1-1.042.018 1.998 1.998 0 0 0-2.83 0l-2.5 2.5a1.998 1.998 0 0 0 0 2.83Z\"\u003e\u003c/path\u003e\u003c/svg\u003e\n  \u003c/a\u003e\n\u003c/h2\u003e\u003cpre\u003e\u003ccode\u003e▸ .github/       # GitHub configuration\n▸ archetypes/    # page archetypes (like scaffolds of archetypes)\n▸ assets/        # css, js, third-party libraries etc.\n▸ config/        # configuration files\n▸ content/       # markdown files for hugo project\n▸ data/          # blog data (allow: yaml, json, toml), e.g. friends.yml\n▸ public/        # build directory\n▸ static/        # static files, e.g. favicon.ico\n▸ themes/        # theme submodules\u003c/code\u003e\u003c/pre\u003e\u003ch2 class=\"heading-element\" id=\"快速入门\"\u003e\u003cspan\u003e快速入门\u003c/span\u003e\n  \u003ca href=\"#%e5%bf%ab%e9%80%9f%e5%85%a5%e9%97%a8\" class=\"heading-mark\"\u003e\n    \u003csvg class=\"octicon octicon-link\" viewBox=\"0 0 16 16\" version=\"1.1\" width=\"16\" height=\"16\" aria-hidden=\"true\"\u003e\u003cpath d=\"m7.775 3.275 1.25-1.25a3.5 3.5 0 1 1 4.95 4.95l-2.5 2.5a3.5 3.5 0 0 1-4.95 0 .751.751 0 0 1 .018-1.042.751.751 0 0 1 1.042-.018 1.998 1.998 0 0 0 2.83 0l2.5-2.5a2.002 2.002 0 0 0-2.83-2.83l-1.25 1.25a.751.751 0 0 1-1.042-.018.751.751 0 0 1-.018-1.042Zm-4.69 9.64a1.998 1.998 0 0 0 2.83 0l1.25-1.25a.751.751 0 0 1 1.042.018.751.751 0 0 1 .018 1.042l-1.25 1.25a3.5 3.5 0 1 1-4.95-4.95l2.5-2.5a3.5 3.5 0 0 1 4.95 0 .751.751 0 0 1-.018 1.042.751.751 0 0 1-1.042.018 1.998 1.998 0 0 0-2.83 0l-2.5 2.5a1.998 1.998 0 0 0 0 2.83Z\"\u003e\u003c/path\u003e\u003c/svg\u003e\n  \u003c/a\u003e\n\u003c/h2\u003e\u003cp\u003e完整的快速入门请参阅此 \u003ca href=\"https://fixit.lruihao.cn/documentation/getting-started/\" target=\"_blank\" rel=\"external nofollow noopener noreferrer\"\u003e页面\u003ci class=\"fa-solid fa-external-link-alt fa-xs ms-1 text-secondary\" aria-hidden=\"true\"\u003e\u003c/i\u003e\u003c/a\u003e。\u003c/p\u003e"},{"title":"📄 The open-source repo for fixit.lruihao.cn","date_published":"2022-07-23T12:17:06Z","date_modified":"2026-03-20T10:49:11Z","id":"https://lruihao.cn/projects/hugo-fixit/docs/","url":"https://lruihao.cn/projects/hugo-fixit/docs/","authors":[{"name":"hugo-fixit","url":"https://github.com/hugo-fixit","avatar":"https://avatars.githubusercontent.com/u/110414864?v=4"}],"tags":["documentation","hugo","hugo-blog","hugo-fixit"],"summary":"FixIt 主题文档 👉 中文 | English\nFixIt 主题文档主要分为：文档、教程 两大板块，欢迎大家发起 PR 完善主题文档。\n系统依赖 Node.js: \u0026gt;= 20.0.0 Go Hugo: \u0026gt;= 0.156.0 (extended version) 贡献文档 首先，点击 fork 按钮 fork 本仓库。\n","content_html":"\u003ch2 class=\"heading-element\" id=\"fixit-主题文档\" data-decreased\u003e\u003cspan\u003eFixIt 主题文档\u003c/span\u003e\n  \u003ca href=\"#fixit-%e4%b8%bb%e9%a2%98%e6%96%87%e6%a1%a3\" class=\"heading-mark\"\u003e\n    \u003csvg class=\"octicon octicon-link\" viewBox=\"0 0 16 16\" version=\"1.1\" width=\"16\" height=\"16\" aria-hidden=\"true\"\u003e\u003cpath d=\"m7.775 3.275 1.25-1.25a3.5 3.5 0 1 1 4.95 4.95l-2.5 2.5a3.5 3.5 0 0 1-4.95 0 .751.751 0 0 1 .018-1.042.751.751 0 0 1 1.042-.018 1.998 1.998 0 0 0 2.83 0l2.5-2.5a2.002 2.002 0 0 0-2.83-2.83l-1.25 1.25a.751.751 0 0 1-1.042-.018.751.751 0 0 1-.018-1.042Zm-4.69 9.64a1.998 1.998 0 0 0 2.83 0l1.25-1.25a.751.751 0 0 1 1.042.018.751.751 0 0 1 .018 1.042l-1.25 1.25a3.5 3.5 0 1 1-4.95-4.95l2.5-2.5a3.5 3.5 0 0 1 4.95 0 .751.751 0 0 1-.018 1.042.751.751 0 0 1-1.042.018 1.998 1.998 0 0 0-2.83 0l-2.5 2.5a1.998 1.998 0 0 0 0 2.83Z\"\u003e\u003c/path\u003e\u003c/svg\u003e\n  \u003c/a\u003e\n\u003c/h2\u003e\u003cp\u003e\u003ca href=\"https://fixit.lruihao.cn/\" target=\"_blank\" rel=\"external nofollow noopener noreferrer\"\u003e\u003cimg loading=\"lazy\" src='/images/remote/Production_8233419177081912330.svg' alt=\"Production environment\"\u003e\u003c/a\u003e\n\u003ca href=\"https://gohugo.io/\" target=\"_blank\" rel=\"external nofollow noopener noreferrer\"\u003e\u003cimg loading=\"lazy\" src='/images/remote/Hugo-%5E0.156_9344247532829321537.svg' alt=\"Hugo\"\u003e\u003c/a\u003e\u003c/p\u003e\n\u003cp\u003e👉 中文 | \u003ca href=\"README.en.md\"\u003eEnglish\u003c/a\u003e\u003c/p\u003e\n\u003cp\u003e\u003ca href=\"https://github.com/hugo-fixit/FixIt\" target=\"_blank\" rel=\"external nofollow noopener noreferrer\"\u003eFixIt\u003ci class=\"fa-solid fa-external-link-alt fa-xs ms-1 text-secondary\" aria-hidden=\"true\"\u003e\u003c/i\u003e\u003c/a\u003e 主题文档主要分为：\u003ca href=\"https://fixit.lruihao.cn/zh-cn/documentation/\" target=\"_blank\" rel=\"external nofollow noopener noreferrer\"\u003e文档\u003ci class=\"fa-solid fa-external-link-alt fa-xs ms-1 text-secondary\" aria-hidden=\"true\"\u003e\u003c/i\u003e\u003c/a\u003e、\u003ca href=\"https://fixit.lruihao.cn/zh-cn/guides/\" target=\"_blank\" rel=\"external nofollow noopener noreferrer\"\u003e教程\u003ci class=\"fa-solid fa-external-link-alt fa-xs ms-1 text-secondary\" aria-hidden=\"true\"\u003e\u003c/i\u003e\u003c/a\u003e 两大板块，欢迎大家发起 PR 完善主题文档。\u003c/p\u003e\n\u003ch2 class=\"heading-element\" id=\"系统依赖\"\u003e\u003cspan\u003e系统依赖\u003c/span\u003e\n  \u003ca href=\"#%e7%b3%bb%e7%bb%9f%e4%be%9d%e8%b5%96\" class=\"heading-mark\"\u003e\n    \u003csvg class=\"octicon octicon-link\" viewBox=\"0 0 16 16\" version=\"1.1\" width=\"16\" height=\"16\" aria-hidden=\"true\"\u003e\u003cpath d=\"m7.775 3.275 1.25-1.25a3.5 3.5 0 1 1 4.95 4.95l-2.5 2.5a3.5 3.5 0 0 1-4.95 0 .751.751 0 0 1 .018-1.042.751.751 0 0 1 1.042-.018 1.998 1.998 0 0 0 2.83 0l2.5-2.5a2.002 2.002 0 0 0-2.83-2.83l-1.25 1.25a.751.751 0 0 1-1.042-.018.751.751 0 0 1-.018-1.042Zm-4.69 9.64a1.998 1.998 0 0 0 2.83 0l1.25-1.25a.751.751 0 0 1 1.042.018.751.751 0 0 1 .018 1.042l-1.25 1.25a3.5 3.5 0 1 1-4.95-4.95l2.5-2.5a3.5 3.5 0 0 1 4.95 0 .751.751 0 0 1-.018 1.042.751.751 0 0 1-1.042.018 1.998 1.998 0 0 0-2.83 0l-2.5 2.5a1.998 1.998 0 0 0 0 2.83Z\"\u003e\u003c/path\u003e\u003c/svg\u003e\n  \u003c/a\u003e\n\u003c/h2\u003e\u003cul\u003e\n\u003cli\u003e\u003ca href=\"https://nodejs.org/\" target=\"_blank\" rel=\"external nofollow noopener noreferrer\"\u003eNode.js\u003ci class=\"fa-solid fa-external-link-alt fa-xs ms-1 text-secondary\" aria-hidden=\"true\"\u003e\u003c/i\u003e\u003c/a\u003e: \u0026gt;= 20.0.0\u003c/li\u003e\n\u003cli\u003e\u003ca href=\"https://go.dev/dl/\" target=\"_blank\" rel=\"external nofollow noopener noreferrer\"\u003eGo\u003ci class=\"fa-solid fa-external-link-alt fa-xs ms-1 text-secondary\" aria-hidden=\"true\"\u003e\u003c/i\u003e\u003c/a\u003e\u003c/li\u003e\n\u003cli\u003e\u003ca href=\"https://gohugo.io/installation/\" target=\"_blank\" rel=\"external nofollow noopener noreferrer\"\u003eHugo\u003ci class=\"fa-solid fa-external-link-alt fa-xs ms-1 text-secondary\" aria-hidden=\"true\"\u003e\u003c/i\u003e\u003c/a\u003e: \u0026gt;= 0.156.0 (extended version)\u003c/li\u003e\n\u003c/ul\u003e\n\u003ch2 class=\"heading-element\" id=\"贡献文档\"\u003e\u003cspan\u003e贡献文档\u003c/span\u003e\n  \u003ca href=\"#%e8%b4%a1%e7%8c%ae%e6%96%87%e6%a1%a3\" class=\"heading-mark\"\u003e\n    \u003csvg class=\"octicon octicon-link\" viewBox=\"0 0 16 16\" version=\"1.1\" width=\"16\" height=\"16\" aria-hidden=\"true\"\u003e\u003cpath d=\"m7.775 3.275 1.25-1.25a3.5 3.5 0 1 1 4.95 4.95l-2.5 2.5a3.5 3.5 0 0 1-4.95 0 .751.751 0 0 1 .018-1.042.751.751 0 0 1 1.042-.018 1.998 1.998 0 0 0 2.83 0l2.5-2.5a2.002 2.002 0 0 0-2.83-2.83l-1.25 1.25a.751.751 0 0 1-1.042-.018.751.751 0 0 1-.018-1.042Zm-4.69 9.64a1.998 1.998 0 0 0 2.83 0l1.25-1.25a.751.751 0 0 1 1.042.018.751.751 0 0 1 .018 1.042l-1.25 1.25a3.5 3.5 0 1 1-4.95-4.95l2.5-2.5a3.5 3.5 0 0 1 4.95 0 .751.751 0 0 1-.018 1.042.751.751 0 0 1-1.042.018 1.998 1.998 0 0 0-2.83 0l-2.5 2.5a1.998 1.998 0 0 0 0 2.83Z\"\u003e\u003c/path\u003e\u003c/svg\u003e\n  \u003c/a\u003e\n\u003c/h2\u003e\u003cp\u003e首先，点击 fork 按钮 fork 本仓库。\u003c/p\u003e"},{"title":"🔧 A clean, elegant but advanced blog theme for Hugo 一个简洁、优雅且高效的 Hugo 主题","date_published":"2021-12-16T03:35:27Z","date_modified":"2026-03-21T13:42:35Z","id":"https://lruihao.cn/projects/hugo-fixit/fixit/","url":"https://lruihao.cn/projects/hugo-fixit/fixit/","authors":[{"name":"hugo-fixit","url":"https://github.com/hugo-fixit","avatar":"https://avatars.githubusercontent.com/u/110414864?v=4"}],"tags":["algolia","blog","giscus","hugo","hugo-blog","hugo-blog-theme","hugo-fixit","hugo-theme","pwa","pwa-app"],"summary":" FixIt 是一个简洁、优雅且高效的 Hugo 博客主题。\n如果你喜欢这个主题，别忘了留下一颗 ⭐️ 哦，谢谢！ English | 简体中文 | 繁體中文 | Français | Русский язык | Español | हिन्दी | deutsch | 한국어 | しろうと FixIt 它的原型基于 LoveIt 主题，KeepIt 主题和 LeaveIt 主题。\n","content_html":"\u003c!-- markdownlint-disable-file MD033 MD041 --\u003e\n\u003cp\u003e\u003cimg loading=\"lazy\" src='/images/remote/apple-devices-preview_2924900667091928771.png' alt=\"Hugo Theme FixIt\" height=\"1158\" width=\"2007\"\u003e\u003c/p\u003e\n\u003cdiv align=\"center\" class=\"ignore\"\u003e\n  \u003cp\u003e\n    FixIt 是一个简洁、优雅且高效的 \u003ca href=\"https://gohugo.io/\"\u003eHugo\u003c/a\u003e 博客主题。\u003cbr\u003e\n    \u003cem\u003e\u003csub\u003e如果你喜欢这个主题，别忘了留下一颗 ⭐️ 哦，谢谢！\u003c/sub\u003e\u003c/em\u003e\n  \u003c/p\u003e\n  \u003ca href=\"https://raw.githubusercontent.com/hugo-fixit/FixIt/refs/heads/main/README.md\"\u003eEnglish\u003c/a\u003e |\n  简体中文 |\n  \u003ca href=\"https://fixit.lruihao.cn/zh-cn/ecosystem/hugo-fixit/fixit/?lang=chinese_traditional\"\u003e繁體中文\u003c/a\u003e |\n  \u003ca href=\"https://fixit.lruihao.cn/ecosystem/hugo-fixit/fixit/?lang=french\"\u003eFrançais\u003c/a\u003e |\n  \u003ca href=\"https://fixit.lruihao.cn/ecosystem/hugo-fixit/fixit/?lang=russian\"\u003eРусский язык\u003c/a\u003e |\n  \u003ca href=\"https://fixit.lruihao.cn/ecosystem/hugo-fixit/fixit/?lang=spanish\"\u003eEspañol\u003c/a\u003e |\n  \u003ca href=\"https://fixit.lruihao.cn/ecosystem/hugo-fixit/fixit/?lang=hindi\"\u003eहिन्दी\u003c/a\u003e |\n  \u003ca href=\"https://fixit.lruihao.cn/ecosystem/hugo-fixit/fixit/?lang=deutsch\"\u003edeutsch\u003c/a\u003e |\n  \u003ca href=\"https://fixit.lruihao.cn/ecosystem/hugo-fixit/fixit/?lang=korean\"\u003e한국어\u003c/a\u003e |\n  \u003ca href=\"https://fixit.lruihao.cn/ecosystem/hugo-fixit/fixit/?lang=japanese\"\u003eしろうと\u003c/a\u003e\n\u003c/div\u003e\n\u003cp\u003e\u003ca title=\"FixIt 官网\" href=\"https://fixit.lruihao.cn/zh-cn/\"\u003e\u003cimg align=\"right\" alt=\"FixIt logo\" width=\"70\" height=\"70\" src=\"https://avatars.githubusercontent.com/u/110414864?s=200\u0026v=4\"\u003e\u003c/a\u003e\u003c/p\u003e\n\u003ch2 class=\"heading-element\" id=\"fixit\" data-decreased\u003e\u003cspan\u003eFixIt\u003c/span\u003e\n  \u003ca href=\"#fixit\" class=\"heading-mark\"\u003e\n    \u003csvg class=\"octicon octicon-link\" viewBox=\"0 0 16 16\" version=\"1.1\" width=\"16\" height=\"16\" aria-hidden=\"true\"\u003e\u003cpath d=\"m7.775 3.275 1.25-1.25a3.5 3.5 0 1 1 4.95 4.95l-2.5 2.5a3.5 3.5 0 0 1-4.95 0 .751.751 0 0 1 .018-1.042.751.751 0 0 1 1.042-.018 1.998 1.998 0 0 0 2.83 0l2.5-2.5a2.002 2.002 0 0 0-2.83-2.83l-1.25 1.25a.751.751 0 0 1-1.042-.018.751.751 0 0 1-.018-1.042Zm-4.69 9.64a1.998 1.998 0 0 0 2.83 0l1.25-1.25a.751.751 0 0 1 1.042.018.751.751 0 0 1 .018 1.042l-1.25 1.25a3.5 3.5 0 1 1-4.95-4.95l2.5-2.5a3.5 3.5 0 0 1 4.95 0 .751.751 0 0 1-.018 1.042.751.751 0 0 1-1.042.018 1.998 1.998 0 0 0-2.83 0l-2.5 2.5a1.998 1.998 0 0 0 0 2.83Z\"\u003e\u003c/path\u003e\u003c/svg\u003e\n  \u003c/a\u003e\n\u003c/h2\u003e\u003cblockquote\u003e\n\u003cp\u003e它的原型基于 \u003ca href=\"https://github.com/dillonzq/LoveIt\" target=\"_blank\" rel=\"external nofollow noopener noreferrer\"\u003eLoveIt\u003ci class=\"fa-solid fa-external-link-alt fa-xs ms-1 text-secondary\" aria-hidden=\"true\"\u003e\u003c/i\u003e\u003c/a\u003e 主题，\u003ca href=\"https://github.com/Fastbyte01/KeepIt\" target=\"_blank\" rel=\"external nofollow noopener noreferrer\"\u003eKeepIt\u003ci class=\"fa-solid fa-external-link-alt fa-xs ms-1 text-secondary\" aria-hidden=\"true\"\u003e\u003c/i\u003e\u003c/a\u003e 主题和 \u003ca href=\"https://github.com/liuzc/LeaveIt\" target=\"_blank\" rel=\"external nofollow noopener noreferrer\"\u003eLeaveIt\u003ci class=\"fa-solid fa-external-link-alt fa-xs ms-1 text-secondary\" aria-hidden=\"true\"\u003e\u003c/i\u003e\u003c/a\u003e 主题。\u003c/p\u003e"},{"title":"Lruihao's Note","date_published":"2021-09-08T12:52:53Z","date_modified":"2026-03-04T08:35:21Z","id":"https://lruihao.cn/projects/lruihao/hugo-blog/","url":"https://lruihao.cn/projects/lruihao/hugo-blog/","authors":[{"name":"Lruihao","url":"https://github.com/Lruihao","avatar":"https://gravatar.loli.net/avatar/fee47a2f4f2cc71f99a02b0a73ecfee0?s=32&amp;d=mp"}],"tags":["blog","front-end","hugo","hugo-blog","hugo-fixit","hugo-site"],"summary":"菠菜眾長 站名“菠菜眾長”，取“兼收並蓄，博採眾長”之意。\nContent 博客内容主要以 Web 前端开发方向为主，分享一些有趣程序、技巧、开发教程、心情和学习记录等。\n","content_html":"\u003ch2 class=\"heading-element\" id=\"菠菜眾長\" data-decreased\u003e\u003cspan\u003e菠菜眾長\u003c/span\u003e\n  \u003ca href=\"#%e8%8f%a0%e8%8f%9c%e7%9c%be%e9%95%b7\" class=\"heading-mark\"\u003e\n    \u003csvg class=\"octicon octicon-link\" viewBox=\"0 0 16 16\" version=\"1.1\" width=\"16\" height=\"16\" aria-hidden=\"true\"\u003e\u003cpath d=\"m7.775 3.275 1.25-1.25a3.5 3.5 0 1 1 4.95 4.95l-2.5 2.5a3.5 3.5 0 0 1-4.95 0 .751.751 0 0 1 .018-1.042.751.751 0 0 1 1.042-.018 1.998 1.998 0 0 0 2.83 0l2.5-2.5a2.002 2.002 0 0 0-2.83-2.83l-1.25 1.25a.751.751 0 0 1-1.042-.018.751.751 0 0 1-.018-1.042Zm-4.69 9.64a1.998 1.998 0 0 0 2.83 0l1.25-1.25a.751.751 0 0 1 1.042.018.751.751 0 0 1 .018 1.042l-1.25 1.25a3.5 3.5 0 1 1-4.95-4.95l2.5-2.5a3.5 3.5 0 0 1 4.95 0 .751.751 0 0 1-.018 1.042.751.751 0 0 1-1.042.018 1.998 1.998 0 0 0-2.83 0l-2.5 2.5a1.998 1.998 0 0 0 0 2.83Z\"\u003e\u003c/path\u003e\u003c/svg\u003e\n  \u003c/a\u003e\n\u003c/h2\u003e\u003cp\u003e\u003ca href=\"https://gohugo.io/\" target=\"_blank\" rel=\"external nofollow noopener noreferrer\"\u003e\u003cimg loading=\"lazy\" src='/images/remote/Hugo-%5E0.147_10197451430892069269.svg' alt=\"Hugo\"\u003e\u003c/a\u003e\n\u003ca href=\"https://github.com/Lruihao/hugo-blog/actions/workflows/deploy.yml\" target=\"_blank\" rel=\"external nofollow noopener noreferrer\"\u003e\u003cimg loading=\"lazy\" src='/images/remote/badge_1895496655215000366.svg' alt=\"Hugo build and deploy\"\u003e\u003c/a\u003e\n\u003ca href=\"https://github.com/Lruihao/hugo-blog/commits/main\" target=\"_blank\" rel=\"external nofollow noopener noreferrer\"\u003e\u003cimg loading=\"lazy\" src='/images/remote/main_9310684978766761497.svg' alt=\"GitHub commit activity (main)\"\u003e\u003c/a\u003e\u003c/p\u003e\n\u003cblockquote\u003e\n\u003cp\u003e站名“菠菜眾長”，取“兼收並蓄，博採眾長”之意。\u003c/p\u003e\n\u003c/blockquote\u003e\n\u003cp\u003e\u003cimg loading=\"lazy\" src='/images/remote/apple-devices-preview_9292544820184326555.webp' alt=\"blog-preview\" height=\"1508\" width=\"2880\"\u003e\u003c/p\u003e\n\u003ch2 class=\"heading-element\" id=\"content\"\u003e\u003cspan\u003eContent\u003c/span\u003e\n  \u003ca href=\"#content\" class=\"heading-mark\"\u003e\n    \u003csvg class=\"octicon octicon-link\" viewBox=\"0 0 16 16\" version=\"1.1\" width=\"16\" height=\"16\" aria-hidden=\"true\"\u003e\u003cpath d=\"m7.775 3.275 1.25-1.25a3.5 3.5 0 1 1 4.95 4.95l-2.5 2.5a3.5 3.5 0 0 1-4.95 0 .751.751 0 0 1 .018-1.042.751.751 0 0 1 1.042-.018 1.998 1.998 0 0 0 2.83 0l2.5-2.5a2.002 2.002 0 0 0-2.83-2.83l-1.25 1.25a.751.751 0 0 1-1.042-.018.751.751 0 0 1-.018-1.042Zm-4.69 9.64a1.998 1.998 0 0 0 2.83 0l1.25-1.25a.751.751 0 0 1 1.042.018.751.751 0 0 1 .018 1.042l-1.25 1.25a3.5 3.5 0 1 1-4.95-4.95l2.5-2.5a3.5 3.5 0 0 1 4.95 0 .751.751 0 0 1-.018 1.042.751.751 0 0 1-1.042.018 1.998 1.998 0 0 0-2.83 0l-2.5 2.5a1.998 1.998 0 0 0 0 2.83Z\"\u003e\u003c/path\u003e\u003c/svg\u003e\n  \u003c/a\u003e\n\u003c/h2\u003e\u003cblockquote\u003e\n\u003cp\u003e博客内容主要以 Web 前端开发方向为主，分享一些有趣程序、技巧、开发教程、心情和学习记录等。\u003c/p\u003e"}]}