{"version":"https://jsonfeed.org/version/1.1","title":"Browser 标签 | 菠菜眾長","description":"Hugo FixIt 作者，喜欢瞎折腾、造轮子、写东西，分享一些前端开发中的所见、所闻、所思。","home_page_url":"https://lruihao.cn/","feed_url":"https://lruihao.cn/tags/browser/feed.json","language":"zh-CN","icon":"https://lruihao.cn/apple-touch-icon.png","favicon":"https://lruihao.cn/favicon.ico","author":{"name":"Lruihao","url":"https://github.com/Lruihao","avatar":"https://lruihao.cn/images/avatar.jpg"},"items":[{"title":"浏览器渲染原理","date_published":"2023-02-05T21:02:52&#43;08:00","date_modified":"2023-12-08T20:26:13&#43;08:00","id":"https://lruihao.cn/posts/browser-rendering/","url":"https://lruihao.cn/posts/browser-rendering/","tags":["Browser","JavaScript","HTML","CSS"],"summary":"1 浏览器是如何渲染页面的？ 当浏览器的网络线程收到 HTML 文档后，会产生一个渲染任务，并将其传递给渲染主线程的消息队列。 在事件循环机制的作用下，渲染主线程取出消息队列中的渲染任务，开启渲染流程。 整个渲染流程分为多个阶段，分别是：HTML 解析、样式计算、布局、分层、绘制、分块、光栅化、画 每个阶段都有明确的输入","content_html":"1 浏览器是如何渲染页面的？ 当浏览器的网络线程收到 HTML 文档后，会产生一个渲染任务，并将其传递给渲染主线程的消息队列。 在事件循环机制的作用下，渲染主线程取出消息队列中的渲染任务，开启渲染流程。 整个渲染流程分为多个阶段，分别是：HTML 解析、样式计算、布局、分层、绘制、分块、光栅化、画 每个阶段都有明确的输入"},{"title":"浏览器原理 - 事件循环","date_published":"2023-01-11T11:16:02&#43;08:00","date_modified":"2023-12-08T20:26:13&#43;08:00","id":"https://lruihao.cn/posts/event-loop/","url":"https://lruihao.cn/posts/event-loop/","tags":["Browser","JavaScript"],"summary":"最近在抖音上刷到很多次 袁进老师 的前端视频，然后就听了一下他的前端大师课，感觉了解一些浏览器原理后，原来工作中的一些疑问也自然解开了。\n","content_html":"最近在抖音上刷到很多次 袁进老师 的前端视频，然后就听了一下他的前端大师课，感觉了解一些浏览器原理后，原来工作中的一些疑问也自然解开了。\n"}]}