{"version":"https://jsonfeed.org/version/1.1","title":"最短路 - 标签 | 菠菜眾長","description":"Hugo FixIt 作者，喜欢瞎折腾、造轮子、写东西，分享一些前端开发中的所见、所闻、所思。","home_page_url":"https://lruihao.cn/","language":"zh-CN","icon":"https://lruihao.cn/apple-touch-icon.png","favicon":"https://lruihao.cn/favicon.ico","authors":[{"name":"Lruihao","url":"https://github.com/Lruihao","avatar":"https://lruihao.cn/images/avatar.jpg"}],"items":[{"title":"Heavy Transportation-poj1797(dijkstra 或最大生成树）","date_published":"2018-08-06T09:42:11&#43;08:00","date_modified":"2023-11-17T20:39:48&#43;08:00","id":"https://lruihao.cn/posts/poj1797/","url":"https://lruihao.cn/posts/poj1797/","authors":[{"name":"Lruihao","url":"https://github.com/Lruihao","avatar":"https://gravatar.loli.net/avatar/fee47a2f4f2cc71f99a02b0a73ecfee0?s=32&amp;d=mp"}],"tags":["ACM","POJ","最短路","C++"],"summary":"题目链接\n大意：\n要从城市 1 到城市 N 运送货物，有 M 条道路，每条道路都有它的最大载重量，问从城市 1 到城市 N 运送最多的重量是多少。\n其实题意很简单，就是找一条 1\u0026ndash;\u0026gt;N 的路径，在不超过每条路径的最大载重量的情况下，使得运送的货物最多。一条路径上的最大载重量为这个路径上权值最小的边； ","content_html":"\u003cp\u003e\u003ca href=\"http://poj.org/problem?id=1797\" target=\"_blank\" rel=\"external nofollow noopener noreferrer\"\u003e题目链接\u003ci class=\"fa-solid fa-external-link-alt fa-fw fa-xs ms-1 text-secondary\" aria-hidden=\"true\"\u003e\u003c/i\u003e\u003c/a\u003e\u003c/p\u003e\n\u003cp\u003e大意：\u003cbr\u003e\n要从城市 1 到城市 N 运送货物，有 M 条道路，每条道路都有它的最大载重量，问从城市 1 到城市 N 运送最多的重量是多少。\u003cbr\u003e\n其实题意很简单，就是找一条 1\u0026ndash;\u0026gt;N 的路径，在不超过每条路径的最大载重量的情况下，使得运送的货物最多。一条路径上的最大载重量为这个路径上权值最小的边；\n\u003ca class=\"lightgallery\" target=\"_blank\" href=\"images/update.jpg\" title=\"更新\" data-thumbnail=\"images/update.jpg\" data-sub-html=\"\u003ch2\u003e更新\u003c/h2\u003e\"\u003e\u003cimg loading=\"lazy\" src='images/update.jpg' alt=\"更新\"\u003e\u003c/a\u003e\u003c/p\u003e"},{"title":"Til the Cows Come Home-poj2387(dijkstra 判断重边）","date_published":"2018-08-03T21:40:33&#43;08:00","date_modified":"2023-11-17T20:39:48&#43;08:00","id":"https://lruihao.cn/posts/poj2387/","url":"https://lruihao.cn/posts/poj2387/","authors":[{"name":"Lruihao","url":"https://github.com/Lruihao","avatar":"https://gravatar.loli.net/avatar/fee47a2f4f2cc71f99a02b0a73ecfee0?s=32&amp;d=mp"}],"tags":["ACM","最短路","C++","C"],"summary":"题目链接\n题目大意：\n说的是，一只奶牛位于 N 号节点，输入 N 个节点和 T 对双向的边，求出由 N 到 1 的最短的距离，其实就是问的单源最短路问题。\n两个点可能有多条路，选择最短的。\n#include #include #include using namespace std; const int INF=99999999; //设为无穷大 int maps[1005][1005],v[1005],d[1005]; //v 表示是否已经过遍历 d 表示从源到点当前最短路 int n; void Dijkstra(int s,int t) { int i,j,k,mini; for(i=1;i\u003c=n;i++) d[i]=INF; //除源点设为 0 距离外 其他先设为无穷大 d[s]=0; for(i=1;i\u003c=n;i++) //n 点循环 n 次 , 找出 n 个 k, 找 n 个点 { mini=INF; k=-1; for(j=1;j\u003c=n;j++) //在所有未标记点中 选 d 值最小的点 if(!v[j] \u0026\u0026 d[j]","content_html":"\u003cp\u003e\u003ca href=\"http://poj.org/problem?id=2387\" target=\"_blank\" rel=\"external nofollow noopener noreferrer\"\u003e题目链接\u003ci class=\"fa-solid fa-external-link-alt fa-fw fa-xs ms-1 text-secondary\" aria-hidden=\"true\"\u003e\u003c/i\u003e\u003c/a\u003e\u003c/p\u003e\n\u003cp\u003e题目大意：\u003cbr\u003e\n说的是，一只奶牛位于 N 号节点，输入 N 个节点和 T 对双向的边，求出由 N 到 1 的最短的距离，其实就是问的单源最短路问题。\u003c/p\u003e\n\u003cp\u003e两个点可能有多条路，选择最短的。\u003c/p\u003e\n\u003cpre\u003e\u003ccode\u003e#include\u003cstdio.h\u003e\n#include\u003cstring.h\u003e\n#include\u003calgorithm\u003e\nusing namespace std;\n\nconst int INF=99999999;                    //设为无穷大\nint maps[1005][1005],v[1005],d[1005];  //v 表示是否已经过遍历 d 表示从源到点当前最短路\nint n;\n\nvoid Dijkstra(int s,int t)\n{\n    int i,j,k,mini;\n    for(i=1;i\u003c=n;i++)\n        d[i]=INF;                      //除源点设为 0 距离外 其他先设为无穷大\n    d[s]=0;\n    for(i=1;i\u003c=n;i++)         //n 点循环 n 次 , 找出 n 个 k, 找 n 个点\n    {\n        mini=INF;\n        k=-1;\n        for(j=1;j\u003c=n;j++)              //在所有未标记点中 选 d 值最小的点\n            if(!v[j] \u0026\u0026 d[j]\u003cmini)\n                mini=d[k=j];\n\n        v[k]=1;                         //标记节点\n        if(k==t)\n        {\n            printf(\"%d\\n\",d[t]);\n            return;\n        }\n        for(j=1;j\u003c=n;j++)\n            if(!v[j] \u0026\u0026 (d[k]+maps[k][j])\u003cd[j])   //表示从 k 出发的点，对于所有边，更新相连点\n                d[j]=d[k]+maps[k][j];\n    }\n}\n\nint main()\n{\n    int T,i,j,x,y,D;\n    while(scanf(\"%d %d\",\u0026T,\u0026n)!=EOF)\n    {\n        memset(v,0,sizeof(v));            //清除标记\n        for(i=1;i\u003c=n;i++)\n            for(j=1;j\u003c=n;j++)\n                maps[i][j]=INF;\n\n        for(i=1;i\u003c=T;i++){\n            scanf(\"%d%d%d\",\u0026x,\u0026y,\u0026D);\n            if(maps[x][y]\u003eD)               //可能有多条路，只记录最短的\n                maps[x][y]=D,maps[y][x]=D;\n        }\n        Dijkstra(1,n);\n    }\n    return 0;\n}\u003c/code\u003e\u003c/pre\u003e"},{"title":"最短路入门","date_published":"2018-08-03T16:27:16&#43;08:00","date_modified":"2023-11-30T23:35:38&#43;08:00","id":"https://lruihao.cn/posts/zuiduanlu/","url":"https://lruihao.cn/posts/zuiduanlu/","authors":[{"name":"Lruihao","url":"https://github.com/Lruihao","avatar":"https://gravatar.loli.net/avatar/fee47a2f4f2cc71f99a02b0a73ecfee0?s=32&amp;d=mp"}],"tags":["最短路","ACM"],"summary":" 1 Dijkstra 算法 1.1 1. 定义概览 Dijkstra（迪杰斯特拉）算法是典型的单源最短路径算法，用于计算一个节点到其他所有节点的最短路径。主要特点是以起始点为中心向外层层扩展，直到扩展到终点为止。Dijkstra 算法是很有代表性的最短路径算法，在很多专业课程中都作为基本内容有详细的介绍，如数据结构，图论，运筹学等等。注意该算法要求图中不存在负权边。\n","content_html":"\u003c!-- markdownlint-disable MD033 --\u003e\n\u003ch2 class=\"heading-element\" id=\"dijkstra-算法\"\u003e\u003cspan\u003e1 Dijkstra 算法\u003c/span\u003e\n  \u003ca href=\"#dijkstra-%e7%ae%97%e6%b3%95\" class=\"heading-mark\"\u003e\n    \u003csvg class=\"octicon octicon-link\" viewBox=\"0 0 16 16\" version=\"1.1\" width=\"16\" height=\"16\" aria-hidden=\"true\"\u003e\u003cpath d=\"m7.775 3.275 1.25-1.25a3.5 3.5 0 1 1 4.95 4.95l-2.5 2.5a3.5 3.5 0 0 1-4.95 0 .751.751 0 0 1 .018-1.042.751.751 0 0 1 1.042-.018 1.998 1.998 0 0 0 2.83 0l2.5-2.5a2.002 2.002 0 0 0-2.83-2.83l-1.25 1.25a.751.751 0 0 1-1.042-.018.751.751 0 0 1-.018-1.042Zm-4.69 9.64a1.998 1.998 0 0 0 2.83 0l1.25-1.25a.751.751 0 0 1 1.042.018.751.751 0 0 1 .018 1.042l-1.25 1.25a3.5 3.5 0 1 1-4.95-4.95l2.5-2.5a3.5 3.5 0 0 1 4.95 0 .751.751 0 0 1-.018 1.042.751.751 0 0 1-1.042.018 1.998 1.998 0 0 0-2.83 0l-2.5 2.5a1.998 1.998 0 0 0 0 2.83Z\"\u003e\u003c/path\u003e\u003c/svg\u003e\n  \u003c/a\u003e\n\u003c/h2\u003e\u003ch3 class=\"heading-element\" id=\"1-定义概览\"\u003e\u003cspan\u003e1.1 1. 定义概览\u003c/span\u003e\n  \u003ca href=\"#1-%e5%ae%9a%e4%b9%89%e6%a6%82%e8%a7%88\" class=\"heading-mark\"\u003e\n    \u003csvg class=\"octicon octicon-link\" viewBox=\"0 0 16 16\" version=\"1.1\" width=\"16\" height=\"16\" aria-hidden=\"true\"\u003e\u003cpath d=\"m7.775 3.275 1.25-1.25a3.5 3.5 0 1 1 4.95 4.95l-2.5 2.5a3.5 3.5 0 0 1-4.95 0 .751.751 0 0 1 .018-1.042.751.751 0 0 1 1.042-.018 1.998 1.998 0 0 0 2.83 0l2.5-2.5a2.002 2.002 0 0 0-2.83-2.83l-1.25 1.25a.751.751 0 0 1-1.042-.018.751.751 0 0 1-.018-1.042Zm-4.69 9.64a1.998 1.998 0 0 0 2.83 0l1.25-1.25a.751.751 0 0 1 1.042.018.751.751 0 0 1 .018 1.042l-1.25 1.25a3.5 3.5 0 1 1-4.95-4.95l2.5-2.5a3.5 3.5 0 0 1 4.95 0 .751.751 0 0 1-.018 1.042.751.751 0 0 1-1.042.018 1.998 1.998 0 0 0-2.83 0l-2.5 2.5a1.998 1.998 0 0 0 0 2.83Z\"\u003e\u003c/path\u003e\u003c/svg\u003e\n  \u003c/a\u003e\n\u003c/h3\u003e\u003cp\u003eDijkstra（迪杰斯特拉）算法是典型的单源最短路径算法，用于计算一个节点到其他所有节点的最短路径。主要特点是以起始点为中心向外层层扩展，直到扩展到终点为止。Dijkstra 算法是很有代表性的最短路径算法，在很多专业课程中都作为基本内容有详细的介绍，如数据结构，图论，运筹学等等。注意该算法要求图中不存在负权边。\u003c/p\u003e"}]}